python_quoine-0.1.4.dist-info/DESCRIPTION.rst
python_quoine-0.1.4.dist-info/METADATA
python_quoine-0.1.4.dist-info/RECORD
python_quoine-0.1.4.dist-info/WHEEL
python_quoine-0.1.4.dist-info/metadata.json
python_quoine-0.1.4.dist-info/top_level.txt
quoine/__init__.py
quoine/client.py
quoine/exceptions.py
quoine/websockets.py
